testpkg2_ftcao/__init__.py
testpkg2_ftcao/testpkg2_ftcao.py
testpkg2_ftcao-0.1.0.dist-info/LICENSE
testpkg2_ftcao-0.1.0.dist-info/METADATA
testpkg2_ftcao-0.1.0.dist-info/WHEEL
testpkg2_ftcao-0.1.0.dist-info/RECORD
